py_lostark-0.2.0.dist-info/licenses/LICENSE
pyloa/__init__.py
pyloa/client.py
pyloa/exceptions.py
pyloa/endpoints/__init__.py
pyloa/endpoints/armories.py
pyloa/endpoints/auctions.py
pyloa/endpoints/base.py
pyloa/endpoints/characters.py
pyloa/endpoints/game_contents.py
pyloa/endpoints/markets.py
pyloa/endpoints/news.py
pyloa/models/__init__.py
pyloa/models/armory.py
pyloa/models/auction.py
pyloa/models/base.py
pyloa/models/character.py
pyloa/models/game_content.py
pyloa/models/market.py
pyloa/models/news.py
py_lostark-0.2.0.dist-info/METADATA
py_lostark-0.2.0.dist-info/WHEEL
py_lostark-0.2.0.dist-info/top_level.txt
py_lostark-0.2.0.dist-info/RECORD
